{
    "code": 0,
    "goods": [
        {
            "gname": "小白菜",
            "gid": "785855",
            "gpicture": "https://timgsa.baidu.com/timg?image&quality=80&size=b9999_10000&sec=1604742855837&di=c43575105694982492421a9b9765b2f9&imgtype=0&src=http%3A%2F%2Fbpic.588ku.com%2Felement_origin_min_pic%2F16%2F10%2F24%2F294675905dd561940d9ba1360cbb9728.jpg",
            "gprice": "5.00",
            "gnum": 1,
            "gweight": "500"
        },
        {
            "gname": "小白菜",
            "gid": "785834",
            "gpicture": "https://timgsa.baidu.com/timg?image&quality=80&size=b9999_10000&sec=1604743024771&di=67f9451baaff7016a128f105ad31555a&imgtype=0&src=http%3A%2F%2Fpic.soutu123.cn%2Felement_origin_min_pic%2F17%2F03%2F09%2F06e9d48eb5dd53c3f8e61b6540de2ada.jpg%2521%2Ffw%2F700%2Fquality%2F90%2Funsharp%2Ftrue%2Fcompress%2Ftrue",
            "gprice": "5.00",
            "gnum": 1,
            "gweight": "500"
        },
        {
            "gname": "小白菜",
            "gid": "786082",
            "gpicture": "http://www.geilisx.com/uploads/images/products/1487578110.jpg",
            "gprice": "5.00",
            "gnum": 1,
            "gweight": "500"
        },
        {
            "gname": "小白菜",
            "gid": "778816",
            "gpicture": "http://pml175b83.pic33.websiteonline.cn/upload/hx07.jpg",
            "gprice": "5.00",
            "gnum": 1,
            "gweight": "500"
        },
        {
            "gname": "小白菜",
            "gid": "801048",
            "gpicture": "http://img13.yiguoimg.com/d/items/2019/190604/9288738172053188_300.jpg",
            "gprice": "5.00",
            "gnum": 1,
            "gweight": "9.00"
        },
        {
            "gname": "小白菜",
            "gid": "780819",
            "gpicture": "http://img12.yiguoimg.com/d/items/2018/181126/9288734582842746_300.jpg",
            "gprice": "5.00",
            "gnum": 1,
            "gweight": "500"
        },
        {
            "gname": "小白菜",
            "gid": "775734",
            "gpicture": "http://img06.yiguoimg.com/e/web/170302/212816/170302212816917_425788_300.jpg",
            "gprice": "5.00",
            "gnum": 1,
            "gweight": "500"
        },
        {
            "gname": "小白菜",
            "gid": "808716",
            "gpicture": "http://pml175b83.pic33.websiteonline.cn/upload/tujian01.jpg",
            "gprice": "5.00",
            "gnum": 1,
            "gweight": "9.00"
        },
        {
            "gname": "小白菜",
            "gid": "778785",
            "gpicture": "http://pml175b83.pic33.websiteonline.cn/upload/rl05.jpg",
            "gprice": "5.00",
            "gnum": 1,
            "gweight": "500"
        },
        {
            "gname": "小白菜",
            "gid": "216633",
            "gpicture": "http://pml175b83.pic33.websiteonline.cn/upload/ly05.jpg",
            "gprice": "5.00",
            "gnum": 1,
            "gweight": "9.00"
        },
        {
            "gname": "小白菜",
            "gid": "835381",
            "gpicture": "http://pml175b83.pic33.websiteonline.cn/upload/ly02.jpg",
            "gprice": "5.00",
            "gnum": 1,
            "gweight": "9.00"
        },
        {
            "gname": "小白菜",
            "gid": "773496",
            "gpicture": "http://www.shikefood.com/includes/ueditor/php/../../../bdimages/upload1/20180123/1516688111346077.jpg",
            "gprice": "5.00",
            "gnum": 1,
            "gweight": "9.00"
        },
        {
            "gname": "小白菜",
            "gid": "789140",
            "gpicture": "http://img14.yiguoimg.com/d/items/2019/190507/9288737938941607_300.jpg",
            "gprice": "5.00",
            "gnum": 1,
            "gweight": "9.00"
        },
        {
            "gname": "小白菜",
            "gid": "769836",
            "gpicture": "http://img10.yiguoimg.com/d/items/2018/181108/9288733757351272_300.jpg",
            "gprice": "5.00",
            "gnum": 1,
            "gweight": "9.00"
        },
        {
            "gname": "小白菜",
            "gid": "837068",
            "gpicture": "http://img14.yiguoimg.com/d/items/2019/190611/9288738214061771_300.jpg",
            "gprice": "5.00",
            "gnum": 1,
            "gweight": "9.00"
        },
        {
            "gname": "小白菜",
            "gid": "798225",
            "gpicture": "http://img05.yiguoimg.com/d/others/180911/9288730997531947.jpg",
            "gprice": "5.00",
            "gnum": 1,
            "gweight": "9.00"
        },
        {
            "gname": "小白菜",
            "gid": "837729",
            "gpicture": "http://img07.yiguoimg.com/e/others/160314/9288692890443886.jpg",
            "gprice": "5.00",
            "gnum": 1,
            "gweight": "9.00"
        },
        {
            "gname": "小白菜",
            "gid": "776491",
            "gpicture": "http://img07.yiguoimg.com/d/others/180115/9288718008132655.jpg",
            "gprice": "5.00",
            "gnum": 1,
            "gweight": "500"
        }
    ]
}